mayil/__init__.py
mayil/core/mayil.py
mayil-0.2.12.dist-info/METADATA
mayil-0.2.12.dist-info/WHEEL
mayil-0.2.12.dist-info/top_level.txt
mayil-0.2.12.dist-info/RECORD
