Metadata-Version: 2.4
Name: mayil
Version: 0.2.12
Summary: A Python library for generating beautiful HTML emails
Home-page: https://github.com/yourusername/mayil
Author: Aravind Suresh
Author-email: your.email@example.com
Classifier: Development Status :: 3 - Alpha
Classifier: Intended Audience :: Developers
Classifier: License :: OSI Approved :: MIT License
Classifier: Operating System :: OS Independent
Classifier: Programming Language :: Python :: 3
Classifier: Programming Language :: Python :: 3.7
Classifier: Programming Language :: Python :: 3.8
Classifier: Programming Language :: Python :: 3.9
Classifier: Programming Language :: Python :: 3.10
Requires-Python: >=3.7
Requires-Dist: pandas>=1.0.0
Requires-Dist: jinja2>=2.11.0
Requires-Dist: premailer>=3.10.0
Requires-Dist: markdown2>=2.4.0
Dynamic: author
Dynamic: author-email
Dynamic: classifier
Dynamic: description
Dynamic: description-content-type
Dynamic: home-page
Dynamic: requires-dist
Dynamic: requires-python
Dynamic: summary
